[
  {
    "id": "11050581604",
    "type": "PushEvent",
    "actor": {
      "id": 137117837,
      "login": "dduyanhhoang",
      "display_login": "dduyanhhoang",
      "gravatar_id": "",
      "url": "https://api.github.com/users/dduyanhhoang",
      "avatar_url": "https://avatars.githubusercontent.com/u/137117837?"
    },
    "repo": {
      "id": 656326069,
      "name": "dduyanhhoang/dduyanhhoang.github.io",
      "url": "https://api.github.com/repos/dduyanhhoang/dduyanhhoang.github.io"
    },
    "payload": {
      "repository_id": 656326069,
      "push_id": 33342267199,
      "ref": "refs/heads/main",
      "head": "b5869298a746253cf7ea0800e15127679c9e077b",
      "before": "54f2538609d37d77ee047593d8c0f9676c46a729"
    },
    "public": true,
    "created_at": "2026-04-26T03:06:47Z"
  },
  {
    "id": "11050529239",
    "type": "PushEvent",
    "actor": {
      "id": 137117837,
      "login": "dduyanhhoang",
      "display_login": "dduyanhhoang",
      "gravatar_id": "",
      "url": "https://api.github.com/users/dduyanhhoang",
      "avatar_url": "https://avatars.githubusercontent.com/u/137117837?"
    },
    "repo": {
      "id": 656326069,
      "name": "dduyanhhoang/dduyanhhoang.github.io",
      "url": "https://api.github.com/repos/dduyanhhoang/dduyanhhoang.github.io"
    },
    "payload": {
      "repository_id": 656326069,
      "push_id": 33342215006,
      "ref": "refs/heads/main",
      "head": "54f2538609d37d77ee047593d8c0f9676c46a729",
      "before": "a6d0ae1f7030b47cf7f8497569ef5246ad9c4c45"
    },
    "public": true,
    "created_at": "2026-04-26T03:03:40Z"
  },
  {
    "id": "11050156824",
    "type": "PushEvent",
    "actor": {
      "id": 137117837,
      "login": "dduyanhhoang",
      "display_login": "dduyanhhoang",
      "gravatar_id": "",
      "url": "https://api.github.com/users/dduyanhhoang",
      "avatar_url": "https://avatars.githubusercontent.com/u/137117837?"
    },
    "repo": {
      "id": 656326069,
      "name": "dduyanhhoang/dduyanhhoang.github.io",
      "url": "https://api.github.com/repos/dduyanhhoang/dduyanhhoang.github.io"
    },
    "payload": {
      "repository_id": 656326069,
      "push_id": 33341842070,
      "ref": "refs/heads/main",
      "head": "a6d0ae1f7030b47cf7f8497569ef5246ad9c4c45",
      "before": "f3f19ebbd587d266dfd88a8ce5ff565aecb96fa0"
    },
    "public": true,
    "created_at": "2026-04-26T02:41:29Z"
  },
  {
    "id": "11038953286",
    "type": "PushEvent",
    "actor": {
      "id": 137117837,
      "login": "dduyanhhoang",
      "display_login": "dduyanhhoang",
      "gravatar_id": "",
      "url": "https://api.github.com/users/dduyanhhoang",
      "avatar_url": "https://avatars.githubusercontent.com/u/137117837?"
    },
    "repo": {
      "id": 656326069,
      "name": "dduyanhhoang/dduyanhhoang.github.io",
      "url": "https://api.github.com/repos/dduyanhhoang/dduyanhhoang.github.io"
    },
    "payload": {
      "repository_id": 656326069,
      "push_id": 33330625754,
      "ref": "refs/heads/main",
      "head": "f3f19ebbd587d266dfd88a8ce5ff565aecb96fa0",
      "before": "01ff37ed8f2a6d1e95cc0aa82815be4847d48925"
    },
    "public": true,
    "created_at": "2026-04-25T16:37:50Z"
  },
  {
    "id": "11038076856",
    "type": "PushEvent",
    "actor": {
      "id": 137117837,
      "login": "dduyanhhoang",
      "display_login": "dduyanhhoang",
      "gravatar_id": "",
      "url": "https://api.github.com/users/dduyanhhoang",
      "avatar_url": "https://avatars.githubusercontent.com/u/137117837?"
    },
    "repo": {
      "id": 656326069,
      "name": "dduyanhhoang/dduyanhhoang.github.io",
      "url": "https://api.github.com/repos/dduyanhhoang/dduyanhhoang.github.io"
    },
    "payload": {
      "repository_id": 656326069,
      "push_id": 33329748776,
      "ref": "refs/heads/main",
      "head": "01ff37ed8f2a6d1e95cc0aa82815be4847d48925",
      "before": "bd3a1d560e0100bb44513e3bd036ed980f63efa2"
    },
    "public": true,
    "created_at": "2026-04-25T15:57:32Z"
  },
  {
    "id": "8757913644",
    "type": "ForkEvent",
    "actor": {
      "id": 137117837,
      "login": "dduyanhhoang",
      "display_login": "dduyanhhoang",
      "gravatar_id": "",
      "url": "https://api.github.com/users/dduyanhhoang",
      "avatar_url": "https://avatars.githubusercontent.com/u/137117837?"
    },
    "repo": {
      "id": 1070969233,
      "name": "tronghieu/BMAD-METHOD-MINIONS",
      "url": "https://api.github.com/repos/tronghieu/BMAD-METHOD-MINIONS"
    },
    "payload": {
      "action": "forked",
      "forkee": {
        "id": 1220039343,
        "node_id": "R_kgDOSLhSrw",
        "name": "BMAD-METHOD-MINIONS",
        "full_name": "dduyanhhoang/BMAD-METHOD-MINIONS",
        "private": false,
        "owner": {
          "login": "dduyanhhoang",
          "id": 137117837,
          "node_id": "U_kgDOCCxAjQ",
          "avatar_url": "https://avatars.githubusercontent.com/u/137117837?v=4",
          "gravatar_id": "",
          "url": "https://api.github.com/users/dduyanhhoang",
          "html_url": "https://github.com/dduyanhhoang",
          "followers_url": "https://api.github.com/users/dduyanhhoang/followers",
          "following_url": "https://api.github.com/users/dduyanhhoang/following{/other_user}",
          "gists_url": "https://api.github.com/users/dduyanhhoang/gists{/gist_id}",
          "starred_url": "https://api.github.com/users/dduyanhhoang/starred{/owner}{/repo}",
          "subscriptions_url": "https://api.github.com/users/dduyanhhoang/subscriptions",
          "organizations_url": "https://api.github.com/users/dduyanhhoang/orgs",
          "repos_url": "https://api.github.com/users/dduyanhhoang/repos",
          "events_url": "https://api.github.com/users/dduyanhhoang/events{/privacy}",
          "received_events_url": "https://api.github.com/users/dduyanhhoang/received_events",
          "type": "User",
          "user_view_type": "public",
          "site_admin": false
        },
        "html_url": "https://github.com/dduyanhhoang/BMAD-METHOD-MINIONS",
        "description": "BMAD-METHOD Expansion Packs - minion teams",
        "fork": true,
        "url": "https://api.github.com/repos/dduyanhhoang/BMAD-METHOD-MINIONS",
        "forks_url": "https://api.github.com/repos/dduyanhhoang/BMAD-METHOD-MINIONS/forks",
        "keys_url": "https://api.github.com/repos/dduyanhhoang/BMAD-METHOD-MINIONS/keys{/key_id}",
        "collaborators_url": "https://api.github.com/repos/dduyanhhoang/BMAD-METHOD-MINIONS/collaborators{/collaborator}",
        "teams_url": "https://api.github.com/repos/dduyanhhoang/BMAD-METHOD-MINIONS/teams",
        "hooks_url": "https://api.github.com/repos/dduyanhhoang/BMAD-METHOD-MINIONS/hooks",
        "issue_events_url": "https://api.github.com/repos/dduyanhhoang/BMAD-METHOD-MINIONS/issues/events{/number}",
        "events_url": "https://api.github.com/repos/dduyanhhoang/BMAD-METHOD-MINIONS/events",
        "assignees_url": "https://api.github.com/repos/dduyanhhoang/BMAD-METHOD-MINIONS/assignees{/user}",
        "branches_url": "https://api.github.com/repos/dduyanhhoang/BMAD-METHOD-MINIONS/branches{/branch}",
        "tags_url": "https://api.github.com/repos/dduyanhhoang/BMAD-METHOD-MINIONS/tags",
        "blobs_url": "https://api.github.com/repos/dduyanhhoang/BMAD-METHOD-MINIONS/git/blobs{/sha}",
        "git_tags_url": "https://api.github.com/repos/dduyanhhoang/BMAD-METHOD-MINIONS/git/tags{/sha}",
        "git_refs_url": "https://api.github.com/repos/dduyanhhoang/BMAD-METHOD-MINIONS/git/refs{/sha}",
        "trees_url": "https://api.github.com/repos/dduyanhhoang/BMAD-METHOD-MINIONS/git/trees{/sha}",
        "statuses_url": "https://api.github.com/repos/dduyanhhoang/BMAD-METHOD-MINIONS/statuses/{sha}",
        "languages_url": "https://api.github.com/repos/dduyanhhoang/BMAD-METHOD-MINIONS/languages",
        "stargazers_url": "https://api.github.com/repos/dduyanhhoang/BMAD-METHOD-MINIONS/stargazers",
        "contributors_url": "https://api.github.com/repos/dduyanhhoang/BMAD-METHOD-MINIONS/contributors",
        "subscribers_url": "https://api.github.com/repos/dduyanhhoang/BMAD-METHOD-MINIONS/subscribers",
        "subscription_url": "https://api.github.com/repos/dduyanhhoang/BMAD-METHOD-MINIONS/subscription",
        "commits_url": "https://api.github.com/repos/dduyanhhoang/BMAD-METHOD-MINIONS/commits{/sha}",
        "git_commits_url": "https://api.github.com/repos/dduyanhhoang/BMAD-METHOD-MINIONS/git/commits{/sha}",
        "comments_url": "https://api.github.com/repos/dduyanhhoang/BMAD-METHOD-MINIONS/comments{/number}",
        "issue_comment_url": "https://api.github.com/repos/dduyanhhoang/BMAD-METHOD-MINIONS/issues/comments{/number}",
        "contents_url": "https://api.github.com/repos/dduyanhhoang/BMAD-METHOD-MINIONS/contents/{+path}",
        "compare_url": "https://api.github.com/repos/dduyanhhoang/BMAD-METHOD-MINIONS/compare/{base}...{head}",
        "merges_url": "https://api.github.com/repos/dduyanhhoang/BMAD-METHOD-MINIONS/merges",
        "archive_url": "https://api.github.com/repos/dduyanhhoang/BMAD-METHOD-MINIONS/{archive_format}{/ref}",
        "downloads_url": "https://api.github.com/repos/dduyanhhoang/BMAD-METHOD-MINIONS/downloads",
        "issues_url": "https://api.github.com/repos/dduyanhhoang/BMAD-METHOD-MINIONS/issues{/number}",
        "pulls_url": "https://api.github.com/repos/dduyanhhoang/BMAD-METHOD-MINIONS/pulls{/number}",
        "milestones_url": "https://api.github.com/repos/dduyanhhoang/BMAD-METHOD-MINIONS/milestones{/number}",
        "notifications_url": "https://api.github.com/repos/dduyanhhoang/BMAD-METHOD-MINIONS/notifications{?since,all,participating}",
        "labels_url": "https://api.github.com/repos/dduyanhhoang/BMAD-METHOD-MINIONS/labels{/name}",
        "releases_url": "https://api.github.com/repos/dduyanhhoang/BMAD-METHOD-MINIONS/releases{/id}",
        "deployments_url": "https://api.github.com/repos/dduyanhhoang/BMAD-METHOD-MINIONS/deployments",
        "created_at": "2026-04-24T13:34:25Z",
        "updated_at": "2026-04-24T13:34:25Z",
        "pushed_at": "2025-11-25T07:11:21Z",
        "git_url": "git://github.com/dduyanhhoang/BMAD-METHOD-MINIONS.git",
        "ssh_url": "git@github.com:dduyanhhoang/BMAD-METHOD-MINIONS.git",
        "clone_url": "https://github.com/dduyanhhoang/BMAD-METHOD-MINIONS.git",
        "svn_url": "https://github.com/dduyanhhoang/BMAD-METHOD-MINIONS",
        "homepage": null,
        "size": 1166,
        "stargazers_count": 0,
        "watchers_count": 0,
        "language": null,
        "has_issues": false,
        "has_projects": true,
        "has_downloads": true,
        "has_wiki": true,
        "has_pages": false,
        "has_discussions": false,
        "forks_count": 0,
        "mirror_url": null,
        "archived": false,
        "disabled": false,
        "open_issues_count": 0,
        "license": null,
        "allow_forking": true,
        "is_template": false,
        "web_commit_signoff_required": false,
        "has_pull_requests": true,
        "pull_request_creation_policy": "all",
        "topics": [

        ],
        "visibility": "public",
        "forks": 0,
        "open_issues": 0,
        "watchers": 0,
        "default_branch": "main"
      }
    },
    "public": true,
    "created_at": "2026-04-24T13:34:25Z"
  },
  {
    "id": "8757077808",
    "type": "ForkEvent",
    "actor": {
      "id": 137117837,
      "login": "dduyanhhoang",
      "display_login": "dduyanhhoang",
      "gravatar_id": "",
      "url": "https://api.github.com/users/dduyanhhoang",
      "avatar_url": "https://avatars.githubusercontent.com/u/137117837?"
    },
    "repo": {
      "id": 566665684,
      "name": "franneck94/UdemyCppEng",
      "url": "https://api.github.com/repos/franneck94/UdemyCppEng"
    },
    "payload": {
      "action": "forked",
      "forkee": {
        "id": 1220019113,
        "node_id": "R_kgDOSLgDqQ",
        "name": "UdemyCppEng",
        "full_name": "dduyanhhoang/UdemyCppEng",
        "private": false,
        "owner": {
          "login": "dduyanhhoang",
          "id": 137117837,
          "node_id": "U_kgDOCCxAjQ",
          "avatar_url": "https://avatars.githubusercontent.com/u/137117837?v=4",
          "gravatar_id": "",
          "url": "https://api.github.com/users/dduyanhhoang",
          "html_url": "https://github.com/dduyanhhoang",
          "followers_url": "https://api.github.com/users/dduyanhhoang/followers",
          "following_url": "https://api.github.com/users/dduyanhhoang/following{/other_user}",
          "gists_url": "https://api.github.com/users/dduyanhhoang/gists{/gist_id}",
          "starred_url": "https://api.github.com/users/dduyanhhoang/starred{/owner}{/repo}",
          "subscriptions_url": "https://api.github.com/users/dduyanhhoang/subscriptions",
          "organizations_url": "https://api.github.com/users/dduyanhhoang/orgs",
          "repos_url": "https://api.github.com/users/dduyanhhoang/repos",
          "events_url": "https://api.github.com/users/dduyanhhoang/events{/privacy}",
          "received_events_url": "https://api.github.com/users/dduyanhhoang/received_events",
          "type": "User",
          "user_view_type": "public",
          "site_admin": false
        },
        "html_url": "https://github.com/dduyanhhoang/UdemyCppEng",
        "description": null,
        "fork": true,
        "url": "https://api.github.com/repos/dduyanhhoang/UdemyCppEng",
        "forks_url": "https://api.github.com/repos/dduyanhhoang/UdemyCppEng/forks",
        "keys_url": "https://api.github.com/repos/dduyanhhoang/UdemyCppEng/keys{/key_id}",
        "collaborators_url": "https://api.github.com/repos/dduyanhhoang/UdemyCppEng/collaborators{/collaborator}",
        "teams_url": "https://api.github.com/repos/dduyanhhoang/UdemyCppEng/teams",
        "hooks_url": "https://api.github.com/repos/dduyanhhoang/UdemyCppEng/hooks",
        "issue_events_url": "https://api.github.com/repos/dduyanhhoang/UdemyCppEng/issues/events{/number}",
        "events_url": "https://api.github.com/repos/dduyanhhoang/UdemyCppEng/events",
        "assignees_url": "https://api.github.com/repos/dduyanhhoang/UdemyCppEng/assignees{/user}",
        "branches_url": "https://api.github.com/repos/dduyanhhoang/UdemyCppEng/branches{/branch}",
        "tags_url": "https://api.github.com/repos/dduyanhhoang/UdemyCppEng/tags",
        "blobs_url": "https://api.github.com/repos/dduyanhhoang/UdemyCppEng/git/blobs{/sha}",
        "git_tags_url": "https://api.github.com/repos/dduyanhhoang/UdemyCppEng/git/tags{/sha}",
        "git_refs_url": "https://api.github.com/repos/dduyanhhoang/UdemyCppEng/git/refs{/sha}",
        "trees_url": "https://api.github.com/repos/dduyanhhoang/UdemyCppEng/git/trees{/sha}",
        "statuses_url": "https://api.github.com/repos/dduyanhhoang/UdemyCppEng/statuses/{sha}",
        "languages_url": "https://api.github.com/repos/dduyanhhoang/UdemyCppEng/languages",
        "stargazers_url": "https://api.github.com/repos/dduyanhhoang/UdemyCppEng/stargazers",
        "contributors_url": "https://api.github.com/repos/dduyanhhoang/UdemyCppEng/contributors",
        "subscribers_url": "https://api.github.com/repos/dduyanhhoang/UdemyCppEng/subscribers",
        "subscription_url": "https://api.github.com/repos/dduyanhhoang/UdemyCppEng/subscription",
        "commits_url": "https://api.github.com/repos/dduyanhhoang/UdemyCppEng/commits{/sha}",
        "git_commits_url": "https://api.github.com/repos/dduyanhhoang/UdemyCppEng/git/commits{/sha}",
        "comments_url": "https://api.github.com/repos/dduyanhhoang/UdemyCppEng/comments{/number}",
        "issue_comment_url": "https://api.github.com/repos/dduyanhhoang/UdemyCppEng/issues/comments{/number}",
        "contents_url": "https://api.github.com/repos/dduyanhhoang/UdemyCppEng/contents/{+path}",
        "compare_url": "https://api.github.com/repos/dduyanhhoang/UdemyCppEng/compare/{base}...{head}",
        "merges_url": "https://api.github.com/repos/dduyanhhoang/UdemyCppEng/merges",
        "archive_url": "https://api.github.com/repos/dduyanhhoang/UdemyCppEng/{archive_format}{/ref}",
        "downloads_url": "https://api.github.com/repos/dduyanhhoang/UdemyCppEng/downloads",
        "issues_url": "https://api.github.com/repos/dduyanhhoang/UdemyCppEng/issues{/number}",
        "pulls_url": "https://api.github.com/repos/dduyanhhoang/UdemyCppEng/pulls{/number}",
        "milestones_url": "https://api.github.com/repos/dduyanhhoang/UdemyCppEng/milestones{/number}",
        "notifications_url": "https://api.github.com/repos/dduyanhhoang/UdemyCppEng/notifications{?since,all,participating}",
        "labels_url": "https://api.github.com/repos/dduyanhhoang/UdemyCppEng/labels{/name}",
        "releases_url": "https://api.github.com/repos/dduyanhhoang/UdemyCppEng/releases{/id}",
        "deployments_url": "https://api.github.com/repos/dduyanhhoang/UdemyCppEng/deployments",
        "created_at": "2026-04-24T13:11:00Z",
        "updated_at": "2026-04-24T13:11:00Z",
        "pushed_at": "2025-02-19T20:45:33Z",
        "git_url": "git://github.com/dduyanhhoang/UdemyCppEng.git",
        "ssh_url": "git@github.com:dduyanhhoang/UdemyCppEng.git",
        "clone_url": "https://github.com/dduyanhhoang/UdemyCppEng.git",
        "svn_url": "https://github.com/dduyanhhoang/UdemyCppEng",
        "homepage": null,
        "size": 348,
        "stargazers_count": 0,
        "watchers_count": 0,
        "language": null,
        "has_issues": false,
        "has_projects": true,
        "has_downloads": true,
        "has_wiki": true,
        "has_pages": false,
        "has_discussions": false,
        "forks_count": 0,
        "mirror_url": null,
        "archived": false,
        "disabled": false,
        "open_issues_count": 0,
        "license": null,
        "allow_forking": true,
        "is_template": false,
        "web_commit_signoff_required": false,
        "has_pull_requests": true,
        "pull_request_creation_policy": "all",
        "topics": [

        ],
        "visibility": "public",
        "forks": 0,
        "open_issues": 0,
        "watchers": 0,
        "default_branch": "master"
      }
    },
    "public": true,
    "created_at": "2026-04-24T13:11:00Z"
  },
  {
    "id": "10982021897",
    "type": "PushEvent",
    "actor": {
      "id": 137117837,
      "login": "dduyanhhoang",
      "display_login": "dduyanhhoang",
      "gravatar_id": "",
      "url": "https://api.github.com/users/dduyanhhoang",
      "avatar_url": "https://avatars.githubusercontent.com/u/137117837?"
    },
    "repo": {
      "id": 1219627609,
      "name": "GDGoCFPTU2/data-pipeline-lab-sblt",
      "url": "https://api.github.com/repos/GDGoCFPTU2/data-pipeline-lab-sblt"
    },
    "payload": {
      "repository_id": 1219627609,
      "push_id": 33273701526,
      "ref": "refs/heads/main",
      "head": "574a7b156c2909bb5ab6aa318370a4cea87fc559",
      "before": "a201aec3cb907df236e9867c796c05fceb77c73c"
    },
    "public": true,
    "created_at": "2026-04-24T05:26:53Z",
    "org": {
      "id": 278871860,
      "login": "GDGoCFPTU2",
      "gravatar_id": "",
      "url": "https://api.github.com/orgs/GDGoCFPTU2",
      "avatar_url": "https://avatars.githubusercontent.com/u/278871860?"
    }
  },
  {
    "id": "8742591817",
    "type": "MemberEvent",
    "actor": {
      "id": 137117837,
      "login": "dduyanhhoang",
      "display_login": "dduyanhhoang",
      "gravatar_id": "",
      "url": "https://api.github.com/users/dduyanhhoang",
      "avatar_url": "https://avatars.githubusercontent.com/u/137117837?"
    },
    "repo": {
      "id": 1219627609,
      "name": "GDGoCFPTU2/data-pipeline-lab-sblt",
      "url": "https://api.github.com/repos/GDGoCFPTU2/data-pipeline-lab-sblt"
    },
    "payload": {
      "member": {
        "login": "dduyanhhoang",
        "id": 137117837,
        "node_id": "U_kgDOCCxAjQ",
        "avatar_url": "https://avatars.githubusercontent.com/u/137117837?v=4",
        "gravatar_id": "",
        "url": "https://api.github.com/users/dduyanhhoang",
        "html_url": "https://github.com/dduyanhhoang",
        "followers_url": "https://api.github.com/users/dduyanhhoang/followers",
        "following_url": "https://api.github.com/users/dduyanhhoang/following{/other_user}",
        "gists_url": "https://api.github.com/users/dduyanhhoang/gists{/gist_id}",
        "starred_url": "https://api.github.com/users/dduyanhhoang/starred{/owner}{/repo}",
        "subscriptions_url": "https://api.github.com/users/dduyanhhoang/subscriptions",
        "organizations_url": "https://api.github.com/users/dduyanhhoang/orgs",
        "repos_url": "https://api.github.com/users/dduyanhhoang/repos",
        "events_url": "https://api.github.com/users/dduyanhhoang/events{/privacy}",
        "received_events_url": "https://api.github.com/users/dduyanhhoang/received_events",
        "type": "User",
        "user_view_type": "public",
        "site_admin": false
      },
      "action": "added"
    },
    "public": true,
    "created_at": "2026-04-24T05:14:28Z",
    "org": {
      "id": 278871860,
      "login": "GDGoCFPTU2",
      "gravatar_id": "",
      "url": "https://api.github.com/orgs/GDGoCFPTU2",
      "avatar_url": "https://avatars.githubusercontent.com/u/278871860?"
    }
  },
  {
    "id": "10952775832",
    "type": "PushEvent",
    "actor": {
      "id": 137117837,
      "login": "dduyanhhoang",
      "display_login": "dduyanhhoang",
      "gravatar_id": "",
      "url": "https://api.github.com/users/dduyanhhoang",
      "avatar_url": "https://avatars.githubusercontent.com/u/137117837?"
    },
    "repo": {
      "id": 1218576199,
      "name": "dduyanhhoang/Day16-Track2-Assignment",
      "url": "https://api.github.com/repos/dduyanhhoang/Day16-Track2-Assignment"
    },
    "payload": {
      "repository_id": 1218576199,
      "push_id": 33244484079,
      "ref": "refs/heads/main",
      "head": "93bb36b888db569a56ac085eb208a5844f3f7902",
      "before": "a004af1f06d37bbf501b8098c88ec90d20c2dbf3"
    },
    "public": true,
    "created_at": "2026-04-23T13:46:46Z"
  },
  {
    "id": "10952763134",
    "type": "PushEvent",
    "actor": {
      "id": 137117837,
      "login": "dduyanhhoang",
      "display_login": "dduyanhhoang",
      "gravatar_id": "",
      "url": "https://api.github.com/users/dduyanhhoang",
      "avatar_url": "https://avatars.githubusercontent.com/u/137117837?"
    },
    "repo": {
      "id": 1218576199,
      "name": "dduyanhhoang/Day16-Track2-Assignment",
      "url": "https://api.github.com/repos/dduyanhhoang/Day16-Track2-Assignment"
    },
    "payload": {
      "repository_id": 1218576199,
      "push_id": 33244471632,
      "ref": "refs/heads/main",
      "head": "a004af1f06d37bbf501b8098c88ec90d20c2dbf3",
      "before": "f9f52f79770ff99dcce392588bf0c113bb199fe1"
    },
    "public": true,
    "created_at": "2026-04-23T13:46:29Z"
  },
  {
    "id": "8695618130",
    "type": "ForkEvent",
    "actor": {
      "id": 137117837,
      "login": "dduyanhhoang",
      "display_login": "dduyanhhoang",
      "gravatar_id": "",
      "url": "https://api.github.com/users/dduyanhhoang",
      "avatar_url": "https://avatars.githubusercontent.com/u/137117837?"
    },
    "repo": {
      "id": 1218160804,
      "name": "VinUni-AI20k/Day16-Track2-Assignment",
      "url": "https://api.github.com/repos/VinUni-AI20k/Day16-Track2-Assignment"
    },
    "payload": {
      "action": "forked",
      "forkee": {
        "id": 1218576199,
        "node_id": "R_kgDOSKH_Rw",
        "name": "Day16-Track2-Assignment",
        "full_name": "dduyanhhoang/Day16-Track2-Assignment",
        "private": false,
        "owner": {
          "login": "dduyanhhoang",
          "id": 137117837,
          "node_id": "U_kgDOCCxAjQ",
          "avatar_url": "https://avatars.githubusercontent.com/u/137117837?v=4",
          "gravatar_id": "",
          "url": "https://api.github.com/users/dduyanhhoang",
          "html_url": "https://github.com/dduyanhhoang",
          "followers_url": "https://api.github.com/users/dduyanhhoang/followers",
          "following_url": "https://api.github.com/users/dduyanhhoang/following{/other_user}",
          "gists_url": "https://api.github.com/users/dduyanhhoang/gists{/gist_id}",
          "starred_url": "https://api.github.com/users/dduyanhhoang/starred{/owner}{/repo}",
          "subscriptions_url": "https://api.github.com/users/dduyanhhoang/subscriptions",
          "organizations_url": "https://api.github.com/users/dduyanhhoang/orgs",
          "repos_url": "https://api.github.com/users/dduyanhhoang/repos",
          "events_url": "https://api.github.com/users/dduyanhhoang/events{/privacy}",
          "received_events_url": "https://api.github.com/users/dduyanhhoang/received_events",
          "type": "User",
          "user_view_type": "public",
          "site_admin": false
        },
        "html_url": "https://github.com/dduyanhhoang/Day16-Track2-Assignment",
        "description": "Cloud AI infrastructure",
        "fork": true,
        "url": "https://api.github.com/repos/dduyanhhoang/Day16-Track2-Assignment",
        "forks_url": "https://api.github.com/repos/dduyanhhoang/Day16-Track2-Assignment/forks",
        "keys_url": "https://api.github.com/repos/dduyanhhoang/Day16-Track2-Assignment/keys{/key_id}",
        "collaborators_url": "https://api.github.com/repos/dduyanhhoang/Day16-Track2-Assignment/collaborators{/collaborator}",
        "teams_url": "https://api.github.com/repos/dduyanhhoang/Day16-Track2-Assignment/teams",
        "hooks_url": "https://api.github.com/repos/dduyanhhoang/Day16-Track2-Assignment/hooks",
        "issue_events_url": "https://api.github.com/repos/dduyanhhoang/Day16-Track2-Assignment/issues/events{/number}",
        "events_url": "https://api.github.com/repos/dduyanhhoang/Day16-Track2-Assignment/events",
        "assignees_url": "https://api.github.com/repos/dduyanhhoang/Day16-Track2-Assignment/assignees{/user}",
        "branches_url": "https://api.github.com/repos/dduyanhhoang/Day16-Track2-Assignment/branches{/branch}",
        "tags_url": "https://api.github.com/repos/dduyanhhoang/Day16-Track2-Assignment/tags",
        "blobs_url": "https://api.github.com/repos/dduyanhhoang/Day16-Track2-Assignment/git/blobs{/sha}",
        "git_tags_url": "https://api.github.com/repos/dduyanhhoang/Day16-Track2-Assignment/git/tags{/sha}",
        "git_refs_url": "https://api.github.com/repos/dduyanhhoang/Day16-Track2-Assignment/git/refs{/sha}",
        "trees_url": "https://api.github.com/repos/dduyanhhoang/Day16-Track2-Assignment/git/trees{/sha}",
        "statuses_url": "https://api.github.com/repos/dduyanhhoang/Day16-Track2-Assignment/statuses/{sha}",
        "languages_url": "https://api.github.com/repos/dduyanhhoang/Day16-Track2-Assignment/languages",
        "stargazers_url": "https://api.github.com/repos/dduyanhhoang/Day16-Track2-Assignment/stargazers",
        "contributors_url": "https://api.github.com/repos/dduyanhhoang/Day16-Track2-Assignment/contributors",
        "subscribers_url": "https://api.github.com/repos/dduyanhhoang/Day16-Track2-Assignment/subscribers",
        "subscription_url": "https://api.github.com/repos/dduyanhhoang/Day16-Track2-Assignment/subscription",
        "commits_url": "https://api.github.com/repos/dduyanhhoang/Day16-Track2-Assignment/commits{/sha}",
        "git_commits_url": "https://api.github.com/repos/dduyanhhoang/Day16-Track2-Assignment/git/commits{/sha}",
        "comments_url": "https://api.github.com/repos/dduyanhhoang/Day16-Track2-Assignment/comments{/number}",
        "issue_comment_url": "https://api.github.com/repos/dduyanhhoang/Day16-Track2-Assignment/issues/comments{/number}",
        "contents_url": "https://api.github.com/repos/dduyanhhoang/Day16-Track2-Assignment/contents/{+path}",
        "compare_url": "https://api.github.com/repos/dduyanhhoang/Day16-Track2-Assignment/compare/{base}...{head}",
        "merges_url": "https://api.github.com/repos/dduyanhhoang/Day16-Track2-Assignment/merges",
        "archive_url": "https://api.github.com/repos/dduyanhhoang/Day16-Track2-Assignment/{archive_format}{/ref}",
        "downloads_url": "https://api.github.com/repos/dduyanhhoang/Day16-Track2-Assignment/downloads",
        "issues_url": "https://api.github.com/repos/dduyanhhoang/Day16-Track2-Assignment/issues{/number}",
        "pulls_url": "https://api.github.com/repos/dduyanhhoang/Day16-Track2-Assignment/pulls{/number}",
        "milestones_url": "https://api.github.com/repos/dduyanhhoang/Day16-Track2-Assignment/milestones{/number}",
        "notifications_url": "https://api.github.com/repos/dduyanhhoang/Day16-Track2-Assignment/notifications{?since,all,participating}",
        "labels_url": "https://api.github.com/repos/dduyanhhoang/Day16-Track2-Assignment/labels{/name}",
        "releases_url": "https://api.github.com/repos/dduyanhhoang/Day16-Track2-Assignment/releases{/id}",
        "deployments_url": "https://api.github.com/repos/dduyanhhoang/Day16-Track2-Assignment/deployments",
        "created_at": "2026-04-23T02:29:34Z",
        "updated_at": "2026-04-23T13:46:51Z",
        "pushed_at": "2026-04-23T13:46:45Z",
        "git_url": "git://github.com/dduyanhhoang/Day16-Track2-Assignment.git",
        "ssh_url": "git@github.com:dduyanhhoang/Day16-Track2-Assignment.git",
        "clone_url": "https://github.com/dduyanhhoang/Day16-Track2-Assignment.git",
        "svn_url": "https://github.com/dduyanhhoang/Day16-Track2-Assignment",
        "homepage": null,
        "size": 602,
        "stargazers_count": 0,
        "watchers_count": 0,
        "language": "HCL",
        "has_issues": false,
        "has_projects": true,
        "has_downloads": true,
        "has_wiki": true,
        "has_pages": false,
        "has_discussions": false,
        "forks_count": 0,
        "mirror_url": null,
        "archived": false,
        "disabled": false,
        "open_issues_count": 0,
        "license": null,
        "allow_forking": true,
        "is_template": false,
        "web_commit_signoff_required": false,
        "has_pull_requests": true,
        "pull_request_creation_policy": "all",
        "topics": [

        ],
        "visibility": "public",
        "forks": 0,
        "open_issues": 0,
        "watchers": 0,
        "default_branch": "main"
      }
    },
    "public": true,
    "created_at": "2026-04-23T02:29:34Z",
    "org": {
      "id": 271981762,
      "login": "VinUni-AI20k",
      "gravatar_id": "",
      "url": "https://api.github.com/orgs/VinUni-AI20k",
      "avatar_url": "https://avatars.githubusercontent.com/u/271981762?"
    }
  },
  {
    "id": "10880582739",
    "type": "PushEvent",
    "actor": {
      "id": 137117837,
      "login": "dduyanhhoang",
      "display_login": "dduyanhhoang",
      "gravatar_id": "",
      "url": "https://api.github.com/users/dduyanhhoang",
      "avatar_url": "https://avatars.githubusercontent.com/u/137117837?"
    },
    "repo": {
      "id": 656326069,
      "name": "dduyanhhoang/dduyanhhoang.github.io",
      "url": "https://api.github.com/repos/dduyanhhoang/dduyanhhoang.github.io"
    },
    "payload": {
      "repository_id": 656326069,
      "push_id": 33172353511,
      "ref": "refs/heads/main",
      "head": "bd3a1d560e0100bb44513e3bd036ed980f63efa2",
      "before": "fe484924c329ab0770b635f3c5ed59ea6d935e6f"
    },
    "public": true,
    "created_at": "2026-04-22T02:00:50Z"
  }
]
